{"name":"Snipetheweb","body":"# SnipeTheWeb\r\n\r\n## Description\r\nTake a sniper rifle and hunt down those pesky DOM elements\r\n\r\nPress the ` to start shooting away, and press escape to reset everything back when you are done. This works better for websites without too much fancy layouts\r\n\r\n## Links\r\n### Greasemonkey/Chrome script\r\n[http://userscripts.org/scripts/discuss/131924 to install the script.](http://userscripts.org/scripts/discuss/131924 to install the script.)\r\nYou may install this script to use this on any site\r\n### Source\r\n[https://github.com/razorstorm/SnipeTheWeb](https://github.com/razorstorm/SnipeTheWeb)\r\n\r\n### Authors and Contributors\r\n@razorstorm ","tagline":"Take a sniper rifle and hunt down those pesky DOM elements","google":"","note":"Don't delete this file! It's used internally to help with page regeneration."}